neuromeka_indycare/IndyCAREReport.py
neuromeka_indycare/__init__.py
neuromeka_indycare/setup_param.py
neuromeka_indycare/daliworks_software/__init__.py
neuromeka_indycare/daliworks_software/auth.sh
neuromeka_indycare/daliworks_software/domain.on.sh
neuromeka_indycare/daliworks_software/ffmpeg
neuromeka_indycare/daliworks_software/filebrowser.db
neuromeka_indycare/daliworks_software/install.sh
neuromeka_indycare/daliworks_software/kill_process.sh
neuromeka_indycare/daliworks_software/lt
neuromeka_indycare/daliworks_software/mjpg_streamer
neuromeka_indycare/daliworks_software/service.on.sh
neuromeka_indycare/daliworks_software/service_cam.on.sh
neuromeka_indycare/daliworks_software/service_cam_rtsp.on.sh
neuromeka_indycare/daliworks_software/ffmpeg-share/ffprobe.xsd
neuromeka_indycare/daliworks_software/ffmpeg-share/libvpx-1080p.ffpreset
neuromeka_indycare/daliworks_software/ffmpeg-share/libvpx-1080p50_60.ffpreset
neuromeka_indycare/daliworks_software/ffmpeg-share/libvpx-360p.ffpreset
neuromeka_indycare/daliworks_software/ffmpeg-share/libvpx-720p.ffpreset
neuromeka_indycare/daliworks_software/ffmpeg-share/libvpx-720p50_60.ffpreset
neuromeka_indycare/daliworks_software/ffmpeg-share/examples/Makefile
neuromeka_indycare/daliworks_software/ffmpeg-share/examples/README
neuromeka_indycare/daliworks_software/ffmpeg-share/examples/avio_reading.c
neuromeka_indycare/daliworks_software/ffmpeg-share/examples/decoding_encoding.c
neuromeka_indycare/daliworks_software/ffmpeg-share/examples/demuxing_decoding.c
neuromeka_indycare/daliworks_software/ffmpeg-share/examples/extract_mvs.c
neuromeka_indycare/daliworks_software/ffmpeg-share/examples/filter_audio.c
neuromeka_indycare/daliworks_software/ffmpeg-share/examples/filtering_audio.c
neuromeka_indycare/daliworks_software/ffmpeg-share/examples/filtering_video.c
neuromeka_indycare/daliworks_software/ffmpeg-share/examples/metadata.c
neuromeka_indycare/daliworks_software/ffmpeg-share/examples/muxing.c
neuromeka_indycare-0.1.35.dist-info/METADATA
neuromeka_indycare-0.1.35.dist-info/WHEEL
neuromeka_indycare-0.1.35.dist-info/entry_points.txt
neuromeka_indycare-0.1.35.dist-info/top_level.txt
neuromeka_indycare-0.1.35.dist-info/RECORD
