Metadata-Version: 2.1
Name: neuromeka-indycare
Version: 0.1.35
Summary: Neuromeka IndyCare Package
Author: Neuromeka
Author-email: technical-support@neuromeka.com
Classifier: Programming Language :: Python :: 3
Classifier: Programming Language :: Python :: 3.6
Classifier: Programming Language :: Python :: 3.7
Classifier: Programming Language :: Python :: 3.8
Classifier: License :: OSI Approved :: MIT License
Classifier: Operating System :: OS Independent
Requires-Python: >=3.6
Requires-Dist: multiprocess
Requires-Dist: pyyaml
Requires-Dist: neuromeka
Requires-Dist: paho-mqtt ==1.6.1
Requires-Dist: opencv-contrib-python ==4.2.0.32
Requires-Dist: posix-ipc >=1.0.0
Requires-Dist: cryptography ==2.6.1
